LICENSE
README.rst
setup.cfg
setup.py
price_predictor/__init__.py
price_predictor/__main__.py
price_predictor/price_predictor.py
price_predictor.egg-info/PKG-INFO
price_predictor.egg-info/SOURCES.txt
price_predictor.egg-info/dependency_links.txt
price_predictor.egg-info/entry_points.txt
price_predictor.egg-info/requires.txt
price_predictor.egg-info/top_level.txt