Metadata-Version: 2.1
Name: price-predictor
Version: 1.0.6
Summary: Quickly predict the future prices of financial instruments with a customizable LSTM Recurrent Neural Network
Home-page: https://github.com/ludovicolemma/price-predictor
Download-URL: https://github.com/ludovicolemma/price-predictor/archive/refs/tags/v1.0.6.tar.gz
Author: Ludovico Lemma
Author-email: lwdovico@protonmail.com
License: MIT
Keywords: LSTM,Machine Learning,Market Price Prediction,Stock Price Prediction,Financial Forecasting
Classifier: Development Status :: 3 - Alpha
Classifier: Intended Audience :: Financial and Insurance Industry
Classifier: Intended Audience :: Developers
Classifier: Intended Audience :: End Users/Desktop
Classifier: Topic :: Software Development :: Build Tools
Classifier: Topic :: Office/Business :: Financial :: Investment
Classifier: License :: OSI Approved :: MIT License
Classifier: Programming Language :: Python :: 3
Classifier: Programming Language :: Python :: 3.5
Classifier: Programming Language :: Python :: 3.6
Classifier: Programming Language :: Python :: 3.7
Requires-Python: >=3.5
License-File: LICENSE
